labscribe/__init__.py
labscribe/database.py
labscribe/experiment.py
labscribe/googlesheets.py
labscribe/data/db_setup.sql
labscribe-0.4.7.dist-info/METADATA
labscribe-0.4.7.dist-info/WHEEL
labscribe-0.4.7.dist-info/top_level.txt
labscribe-0.4.7.dist-info/RECORD
