Metadata-Version: 2.1
Name: labscribe
Version: 0.4.7
Summary: A small package for managing python experiment scripts
Home-page: https://github.com/jaypmorgan/labscribe
Author: Jay Morgan
Author-email: jay.p.morgan@outlook.com
Requires-Python: >=3
Requires-Dist: gspread (==3.6.0)
